mastdb/__init__.py
mastdb/app.py
mastdb/core/io.py
mastdb/core/repo.py
mastdb/core/upload.py
mastdb/core/utils.py
mastdb/services/experiments.py
mastdb/services/files.py
mastdb/services/numerical_models.py
mastdb/services/references.py
mastdb/services/run_results.py
mastdb/templates/License-cc-by-sa.md
mastdb/templates/missing.png
mastdb-1.0.1.dist-info/LICENSE
mastdb-1.0.1.dist-info/METADATA
mastdb-1.0.1.dist-info/WHEEL
mastdb-1.0.1.dist-info/entry_points.txt
mastdb-1.0.1.dist-info/RECORD
