Metadata-Version: 2.1
Name: mastdb
Version: 1.0.1
Summary: MAsonryShake-Table CLI
License: GPL-3.0-or-later
Author: ymarcon
Author-email: yannick.marcon@epfl.ch
Requires-Python: >=3.10,<4.0
Classifier: License :: OSI Approved :: GNU General Public License v3 or later (GPLv3+)
Classifier: Programming Language :: Python :: 3
Classifier: Programming Language :: Python :: 3.10
Classifier: Programming Language :: Python :: 3.11
Requires-Dist: openpyxl (>=3.1.2,<4.0.0)
Requires-Dist: openpyxl-image-loader (>=1.0.5,<2.0.0)
Requires-Dist: pandas (>=2.1.3,<3.0.0)
Requires-Dist: requests (>=2.31.0,<3.0.0)
Requires-Dist: rich (>=13.7.0,<14.0.0)
Requires-Dist: tqdm (>=4.66.1,<5.0.0)
Requires-Dist: typer (>=0.9.0,<0.10.0)
Requires-Dist: urllib3 (>=2.1.0,<3.0.0)
